LICENSE
README.md
setup.py
src/lazycsv/__init__.py
src/lazycsv/lazycsv.c
src/lazycsv.egg-info/PKG-INFO
src/lazycsv.egg-info/SOURCES.txt
src/lazycsv.egg-info/dependency_links.txt
src/lazycsv.egg-info/requires.txt
src/lazycsv.egg-info/top_level.txt
tests/test_lazycsv.py